{
  "ninebot/Vzmix": "/motomate/photos/Ninebot_Vzmix.d4da485a.png",
  "ninebot/C90": "/motomate/photos/Ninebot_C90.8953f218.png",
  "ninebot/Cz90": "/motomate/photos/Ninebot_Cz90.cf7d0de3.png",
  "ninebot/Bmax90": "/motomate/photos/Ninebot_Bmax90.4dc8f079.png",
  "ninebot/E300p MK2": "/motomate/photos/Ninebot_E300pMK2.9d2ea2f0.png",
  "ninebot/E200p MK2": "/motomate/photos/Ninebot_E200pMK2.8fe9f11e.png",
  "ninebot/E150c MK2": "/motomate/photos/Ninebot_E150cMK2.8e3fea8e.png",
  "ninebot/E100": "/motomate/photos/Ninebot_E80cMK2.dc5696e0.png",
  "ninebot/E80c MK2": "/motomate/photos/Ninebot_E80cMK2.dc5696e0.png",
  "ninebot/M5": "/motomate/photos/Ninebot_M5.05f8ad5d.png",
  "ninebot/M3": "/motomate/photos/Ninebot_M3.005b61c4.png",
  "ninebot/M3 95c Max": "/motomate/photos/Ninebot_M395cMax.2c7ef8e5.png",
  "ninebot/M95c+": "/motomate/photos/Ninebot_M95c.2eae48da.png",
  "ninebot/N3 85c": "/motomate/photos/Ninebot_N385c.a31aeb53.png",
  "ninebot/N85c": "/motomate/photos/Ninebot_N85c.4cd19d64.png",
  "ninebot/Q3 85c": "/motomate/photos/Ninebot_Q385c.52df492e.png",
  "ninebot/Q85c": "/motomate/photos/Ninebot_Q85c.62f2722c.png",
  "ninebot/C85c": "/motomate/photos/Ninebot_C85c.08e61bed.png",
  "NIU/FXT": "/motomate/photos/NIU_FXT.734962c5.png",
  "NIU/FXT (北京)": "/motomate/photos/NIU_FXT.734962c5.png",
  "NIU/F400t": "/motomate/photos/NIU_F400t.49aa716e.png",
  "NIU/F200": "/motomate/photos/NIU_F200.64077512.png",
  "NIU/G400t": "/motomate/photos/NIU_G400t.fce20db6.png",
  "NIU/FX (风速版)": "/motomate/photos/NIU_FX_fs.3a448a68.png",
  "NIU/NX (风速版)": "/motomate/photos/NIU_NX_fs.47573186.png",
  "NIU/FS (风速版)": "/motomate/photos/NIU_FS.3ddb5d5d.png",
  "NIU/NX Hyper": "/motomate/photos/NX%20Hyper.be2452a2.png",
  "NIU/NX": "/motomate/photos/NIU_NX.64abfb20.png",
  "NIU/NL": "/motomate/photos/NIU_NL.9f7660a0.png",
  "NIU/NS": "/motomate/photos/NIU_NS.a78be724.png",
  "NIU/Nplay": "/motomate/photos/NIU_Nplay.97f155a1.png",
  "NIU/N1S": "/motomate/photos/NIU_Nplay.97f155a1.png",
  "NIU/FX 2025": "/motomate/photos/NIU_FX.94b3ec61.png",
  "NIU/FX 2024": "/motomate/photos/NIU_FX.94b3ec61.png",
  "NIU/MQI+": "/motomate/photos/NIU_MQI%2B.37406b66.png",
  "NIU/MQI": "/motomate/photos/NIU_MQI.ea9668c1.png"
}
